fastapi_router_handler/__init__.py
fastapi_router_handler/handlers/__init__.py
fastapi_router_handler/handlers/async_handler.py
fastapi_router_handler/handlers/base.py
fastapi_router_handler/middleware/__init__.py
fastapi_router_handler/middleware/exception_middleware.py
fastapi_router_handler/types/__init__.py
fastapi_router_handler/types/custom_types.py
fastapi_router_handler-0.1.0.dist-info/METADATA
fastapi_router_handler-0.1.0.dist-info/WHEEL
fastapi_router_handler-0.1.0.dist-info/RECORD
