Metadata-Version: 2.1
Name: fastapi_router_handler
Version: 0.1.0
Summary: Python Fastapi's general exception handler
License: MIT-3
Author: KyungHo Kim
Author-email: qqaa3030@gmail.com
Requires-Python: >=3.10,<4.0
Classifier: License :: Other/Proprietary License
Classifier: Programming Language :: Python :: 3
Classifier: Programming Language :: Python :: 3.10
Classifier: Programming Language :: Python :: 3.11
Classifier: Programming Language :: Python :: 3.12
Classifier: Programming Language :: Python :: 3.13
Requires-Dist: fastapi (>=0.115.6,<0.116.0)
Requires-Dist: httpx (>=0.28.1,<0.29.0)
